config/__init__.py
config/core.py
datasets/__init__.py
datasets/heart_failure_clinical_records_dataset.csv
processing/__init__.py
processing/data_manager.py
processing/features.py
processing/validation.py
trained_models/__init__.py
trained_models/patient_survival_model_output_v0.0.4.pkl
survival_model-0.0.4.dist-info/METADATA
survival_model-0.0.4.dist-info/WHEEL
survival_model-0.0.4.dist-info/top_level.txt
survival_model-0.0.4.dist-info/RECORD
