Metadata-Version: 2.4
Name: survival_model
Version: 0.0.4
Summary: Model to predict survival chance of heart patients
Author: Ritam Banik
Author-email: ritam.banik@gmail.com
Maintainer-email: ritam.banik@gmail.com
License: BSD-3
Classifier: License :: OSI Approved :: MIT License
Classifier: Programming Language :: Python
Classifier: Programming Language :: Python :: 3
Classifier: Programming Language :: Python :: 3.7
Classifier: Programming Language :: Python :: 3.8
Classifier: Programming Language :: Python :: 3.9
Classifier: Programming Language :: Python :: 3.10
Classifier: Programming Language :: Python :: 3.11
Classifier: Programming Language :: Python :: 3.13
Classifier: Programming Language :: Python :: Implementation :: CPython
Classifier: Programming Language :: Python :: Implementation :: PyPy
Requires-Python: >=3.7.0
Requires-Dist: joblib==1.4.2
Requires-Dist: numpy==2.2.2
Requires-Dist: pandas==2.2.3
Requires-Dist: xgboost==3.0.0
Requires-Dist: pydantic==2.10.5
Requires-Dist: ruamel.yaml==0.18.10
Requires-Dist: scikit-learn==1.6.1
Requires-Dist: strictyaml==1.7.3
Requires-Dist: gradio
Dynamic: author
Dynamic: author-email
Dynamic: classifier
Dynamic: description
Dynamic: description-content-type
Dynamic: license
Dynamic: maintainer-email
Dynamic: requires-dist
Dynamic: requires-python
Dynamic: summary
